LICENSE
MANIFEST.in
README.md
quicktest.py
settings_test.py
setup.py
django_odnoklassniki_photos.egg-info/PKG-INFO
django_odnoklassniki_photos.egg-info/SOURCES.txt
django_odnoklassniki_photos.egg-info/dependency_links.txt
django_odnoklassniki_photos.egg-info/not-zip-safe
django_odnoklassniki_photos.egg-info/requires.txt
django_odnoklassniki_photos.egg-info/top_level.txt
odnoklassniki_photos/__init__.py
odnoklassniki_photos/__init__.pyc
odnoklassniki_photos/factories.py
odnoklassniki_photos/factories.pyc
odnoklassniki_photos/models.py
odnoklassniki_photos/models.pyc
odnoklassniki_photos/tests.py
odnoklassniki_photos/tests.pyc
odnoklassniki_photos/migrations/0001_initial.py
odnoklassniki_photos/migrations/0001_initial.pyc
odnoklassniki_photos/migrations/0002_auto__del_field_album_like_count__add_field_album_likes_count__del_fie.py
odnoklassniki_photos/migrations/0003_auto__add_field_album_updated__chg_field_album_created__add_index_albu.py
odnoklassniki_photos/migrations/0004_auto__add_field_photo_actions_count.py
odnoklassniki_photos/migrations/0005_calculate_actions_count.py
odnoklassniki_photos/migrations/0005_calculate_actions_count.pyc
odnoklassniki_photos/migrations/__init__.py
odnoklassniki_photos/migrations/__init__.pyc