Metadata-Version: 1.1
Name: django-odnoklassniki-photos
Version: 0.1.5
Summary: Django implementation for odnoklassniki Photo and Album API 
Home-page: https://github.com/ramusus/django-odnoklassniki-photos
Author: ramusus, Romeno
Author-email: ramusus@gmail.com, RomenoEx@gmail.com
License: BSD
Download-URL: http://pypi.python.org/pypi/django-odnoklassniki-photos
Platform: UNKNOWN
Classifier: Development Status :: 4 - Beta
Classifier: Environment :: Web Environment
Classifier: Intended Audience :: Developers
Classifier: License :: OSI Approved :: BSD License
Classifier: Operating System :: OS Independent
Classifier: Programming Language :: Python
Classifier: Topic :: Software Development :: Libraries :: Python Modules
